{
	"_o_": {},
	"- #️⃣ API": {},
	"-👥 NAMESPACE": {},
	"(Clipboard)": {
		"methods": [
			"(4DPop_clipboardHistory)",
			"(clipboard_HISTORY_START)",
			"(clipboard_HISTORY)",
			"(COMPILER_clipboard)"
		],
		"forms": [
			"(CLIPBOARD_HISTORY)"
		]
	},
	"(component)": {
		"groups": [
			"(private)",
			"(public)"
		]
	},
	"(private)": {},
	"(public)": {},
	"(tools)": {},
	"# 🚧 DEV": {},
	"♻️ LIBRAIRIES": {},
	"⚙️ MACROS": {},
	"📦 COMPONENT": {
		"methods": [
			"COMPILER_pasteboard",
			"pastboard_Get_data_Types",
			"pasteboard_drop_viewer",
			"pasteboard_viewer"
		],
		"forms": [
			"pasteboard_drop_viewer",
			"pasteboard_viewer"
		]
	},
	"🛠️ Tools": {
		"methods": [
			"Compiler_tools",
			"noError",
			"Obj_CENTER"
		]
	},
	"4️⃣ 4DPop": {
		"methods": [
			"_4DPopPastebooard",
			"dragContainer",
			"pasteboard"
		]
	},
	"trash": {
		"groups": [
			"(Clipboard)",
			"(component)",
			"(tools)"
		]
	}
}